{"Paul":{"name":"Paul","location":"Berlin","rating":1500,"stats":{"solo":{"win":0,"lose":0},"team":{"win":0,"lose":0}},"teams":[]},"Jens":{"name":"Jens","location":"Berlin","rating":1500,"stats":{"solo":{"win":0,"lose":0},"team":{"win":0,"lose":0}},"teams":[]},"Rene":{"name":"Rene","location":"Berlin","rating":1500,"stats":{"solo":{"win":0,"lose":0},"team":{"win":0,"lose":0}},"teams":[]},"Stefan":{"name":"Stefan","location":"Berlin","rating":1500,"stats":{"solo":{"win":0,"lose":0},"team":{"win":0,"lose":0}},"teams":[]}}